PyCameraList/__init__.py
PyCameraList/camera_device.cp311-win_amd64.pyd
PyCameraList_fork-1.0.0.dist-info/LICENSE
PyCameraList_fork-1.0.0.dist-info/METADATA
PyCameraList_fork-1.0.0.dist-info/WHEEL
PyCameraList_fork-1.0.0.dist-info/top_level.txt
PyCameraList_fork-1.0.0.dist-info/RECORD
